README.rst
setup.py
ukpol_cli.py
ukpol_cli.egg-info/PKG-INFO
ukpol_cli.egg-info/SOURCES.txt
ukpol_cli.egg-info/dependency_links.txt
ukpol_cli.egg-info/entry_points.txt
ukpol_cli.egg-info/requires.txt
ukpol_cli.egg-info/top_level.txt