Metadata-Version: 1.1
Name: ukpol-cli
Version: 0.0.2
Summary: A CLI tool for finding information on UK police forces and local crime information
Home-page: https://github.com/OdinsHat/ukpol-cli
Author: Doug Bromley
Author-email: doug@tintophat.com
License: The MIT License (MIT)
